{
  "title": "Dhokha: Round D Corner",
  "release_date": "2022-09-22",
  "vote_average": 4.6,
  "genres": "Crime, Thriller",
  "overview": "When a delusional housewife with a personality disorder is taken hostage by a terrorist on the loose and a husband accused of cheating on his wife have their own versions of reality, how do we know who's saying the truth?",
  "poster_path": "https://image.tmdb.org/t/p/w500/mcNf2j9e5iDWAfLr7pS9uusgXx5.jpg",
  "imdb_id": "tt10644708",
  "id": 1005581,
  "type": "movie"
}