{
  "title": "She Taught Love",
  "release_date": "2024-09-27",
  "vote_average": 5.2,
  "genres": "Romance, Drama",
  "overview": "Ever since getting off a prestigious cable television series, Frank Cooper has been coasting through life distracting himself with women, booze and blow, while auditioning to play stereotypical gang members and drug dealers. But the minute he meets Mali Waters, a sports agent living for the present, his whole world changes.",
  "poster_path": "https://image.tmdb.org/t/p/w500/hTcsoaYkQnOj6YSPDpeLv9kpaPm.jpg",
  "imdb_id": "tt7983904",
  "id": 1007723,
  "type": "movie"
}