{
  "title": "An Inconvenient Love",
  "release_date": "2022-11-23",
  "vote_average": 5.2,
  "genres": "Romance, Comedy",
  "overview": "Ayef meets Manny. It is at a time where she focuses on her dreams while Manny being a flighty young shop owner, goes with the flow. They both believe love is inconvenient and agree to a contractual fling expiring on the date Ayef leaves for Singapore, but they start falling for one another.",
  "poster_path": "https://image.tmdb.org/t/p/w500/pyLkGGbfkT3tySgN1n9ASqZjRlX.jpg",
  "imdb_id": "tt21801648",
  "id": 1012906,
  "type": "movie"
}