{
  "title": "The Chronicles of Narnia: The Voyage of the Dawn Treader",
  "release_date": "2010-12-02",
  "vote_average": 6.4,
  "genres": "Adventure, Family, Fantasy",
  "overview": "This time around Edmund and Lucy Pevensie, along with their pesky cousin Eustace Scrubb find themselves swallowed into a painting and on to a fantastic Narnian ship headed for the very edges of the world.",
  "poster_path": "https://image.tmdb.org/t/p/w500/z6LVJXEmY8E6s57uf8cV3RlWvws.jpg",
  "imdb_id": "tt0980970",
  "id": 10140,
  "type": "movie"
}