{
  "title": "In the Land of Saints and Sinners",
  "release_date": "2023-10-06",
  "vote_average": 6.52,
  "genres": "Action, Thriller",
  "overview": "In a remote Irish village, a damaged Finbar is forced to fight for redemption after a lifetime of sins, but what price is he willing to pay? In the land of saints and sinners, some sins can't be buried.",
  "poster_path": "https://image.tmdb.org/t/p/w500/uOa6TNXi3LUHrqIp9xiWNyOyyCF.jpg",
  "imdb_id": "tt15782690",
  "id": 1027073,
  "type": "movie"
}