{
  "title": "Anukoni Prayanam",
  "release_date": "2022-10-28",
  "vote_average": 7,
  "genres": "Drama, Action",
  "overview": "Two Telugu-speaking friends with opposing views towards life work at a construction site in Bhubaneswar, Odisha. When one of them dies of a heart attack, the other takes it upon himself to take the body to his friend’s village for last rites. What did he have to endure and experience during the journey, and how did it transform him?",
  "poster_path": "https://image.tmdb.org/t/p/w500/4ZssBWSWr0aYGuuIT2pnhsarkFo.jpg",
  "imdb_id": "tt21331256",
  "id": 1034215,
  "type": "movie"
}