{
  "title": "Nude",
  "release_date": "2010-09-18",
  "vote_average": 6.5,
  "genres": "Drama",
  "overview": "After graduating high school, Hiromi moves from the coastal town of Niigata to Tokyo in the hopes of becoming a famous actress. Her dream seemingly comes true as a manager scouts her off the street. He recruits her as a model but it's actually to be a \"nude\" model. It's not exactly what Hiromi was looking for, but she can't turn down the opportunity. As her career dwindles, the manager coerces her to make the jump to AV and Hiromi gains a new identity as Mihiro.",
  "poster_path": "https://image.tmdb.org/t/p/w500/9qCJ8azp70Eacpcha9yubg98ejq.jpg",
  "imdb_id": "tt1660399",
  "id": 103450,
  "type": "movie"
}