{
  "title": "Shark Tale",
  "release_date": "2004-09-20",
  "vote_average": 6.023,
  "genres": "Animation, Action, Comedy, Family",
  "overview": "Oscar is a small fish whose big aspirations often get him into trouble. Meanwhile, Lenny is a great white shark with a surprising secret that no sea creature would guess: He's a vegetarian. When a lie turns Oscar into an improbable hero and Lenny becomes an outcast, the two form an unlikely friendship.",
  "poster_path": "https://image.tmdb.org/t/p/w500/r08DpyPyhXcJTfNZAICNGMzcQ8l.jpg",
  "imdb_id": "tt0307453",
  "id": 10555,
  "type": "movie"
}