{
  "title": "Futureworld",
  "release_date": "1976-08-13",
  "vote_average": 5.897,
  "genres": "Action, Adventure, Science Fiction, Thriller",
  "overview": "Two years after the Westworld tragedy in the Delos amusement park, the corporate owners have reopened the park following over $1 billion in safety and other improvements. For publicity purposes, reporters Chuck Browning and Tracy Ballard are invited to review the park. Just prior to arriving, however, Browning is given a clue by a dying man that something is amiss.",
  "poster_path": "https://image.tmdb.org/t/p/w500/sH5b8w52rEt8iqc1ibt1SwU5P.jpg",
  "imdb_id": "tt0074559",
  "id": 10640,
  "type": "movie"
}