{
  "title": "Baby Assassins 2",
  "release_date": "2023-03-24",
  "vote_average": 6.75,
  "genres": "Action, Comedy, Crime, Drama",
  "overview": "Chisato and Mahiro must pay four years of overdue fees or lose their membership in their assassin guild. They take part-time jobs, but find themselves in the middle of an armed robbery and being hunted by other assassins.",
  "poster_path": "https://image.tmdb.org/t/p/w500/8BW7KMi9ANWZQicIjov31zyJZ4A.jpg",
  "imdb_id": "tt26920120",
  "id": 1077600,
  "type": "movie"
}