{
  "title": "THE MESSENGER",
  "release_date": "",
  "vote_average": 10,
  "genres": "History, Fantasy, War, Adventure",
  "overview": "The \"Steaua Bucureștiului\" Battalion is trapped in the heart of Germany and runs out of ammunition, food and medicine.  So Private Mihailovici Anton is sent with an important message to the main base, but his journey is not so easy.",
  "poster_path": "https://image.tmdb.org/t/p/w500/5zavc2pugTDaD7vWlub70a4Pgnk.jpg",
  "imdb_id": null,
  "id": 1110610,
  "type": "movie"
}