{
  "title": "Elegy",
  "release_date": "2008-08-08",
  "vote_average": 6.294,
  "genres": "Drama, Romance",
  "overview": "Cultural critic David Kepesh finds his life -- which he indicates is a state of \"emancipated manhood\" -- thrown into tragic disarray by Consuela Castillo, a well-mannered student who awakens a sense of sexual possessiveness in her teacher.",
  "poster_path": "https://image.tmdb.org/t/p/w500/roHAoE1TXpUzSolJrjgtmLQbmjS.jpg",
  "imdb_id": "tt0974554",
  "id": 11671,
  "type": "movie"
}