{
  "title": "Lost and Found",
  "release_date": "1996-10-18",
  "vote_average": 7.1,
  "genres": "Drama, Romance",
  "overview": "A woman diagnosed with leukemia meets a Chinese-Scottish sailor who she loses contact with. In order to find him she enlists Worm, a man who runs a “lost and found” business, and the two set out to find what she’s looking for.",
  "poster_path": "https://image.tmdb.org/t/p/w500/jJSJhFBp5FYZnq72CPg6xSVJZgq.jpg",
  "imdb_id": "tt0117904",
  "id": 118202,
  "type": "movie"
}