{
  "title": "Tampopo",
  "release_date": "1985-11-23",
  "vote_average": 7.853,
  "genres": "Comedy",
  "overview": "In this humorous paean to the joys of food, a pair of truck drivers happen onto a decrepit roadside shop selling ramen noodles. The widowed owner, Tampopo, begs them to help her turn her establishment into a paragon of the \"art of noodle-soup making\". Interspersed are satirical vignettes about the importance of food to different aspects of human life.",
  "poster_path": "https://image.tmdb.org/t/p/w500/2XLDb3RDQmtlxt5Snnig9W4moq4.jpg",
  "imdb_id": "tt0092048",
  "id": 11830,
  "type": "movie"
}