{
  "title": "Intimacy",
  "release_date": "2001-01-20",
  "vote_average": 6.3,
  "genres": "Romance, Drama, Fantasy",
  "overview": "Jay, a failed musician, walked out of his family and now earns a living as head bartender in a trendy London pub. Every Wednesday afternoon a woman comes to his house for graphic, almost wordless, sex. One day Jay follows her and finds out about the rest of her life. This eventually disrupts their relationship.",
  "poster_path": "https://image.tmdb.org/t/p/w500/I0mlv1FahaLJqu2ByffMXEn4NN.jpg",
  "imdb_id": "tt0256103",
  "id": 11845,
  "type": "movie"
}