{
  "title": "Saw V",
  "release_date": "2008-10-23",
  "vote_average": 6.171,
  "genres": "Horror, Thriller, Crime",
  "overview": "Following Jigsaw's grisly demise, Detective Mark Hoffman is commended as a hero, but Agent Strahm is suspicious, and delves into Hoffman's past. Meanwhile, another group of people are put through a series of gruesome tests.",
  "poster_path": "https://image.tmdb.org/t/p/w500/rKl79KqLXg60KFyKsLe4wSSjQ08.jpg",
  "imdb_id": "tt1132626",
  "id": 11917,
  "type": "movie"
}