{
  "title": "In a Violent Nature",
  "release_date": "2024-05-31",
  "vote_average": 5.9,
  "genres": "Horror, Thriller",
  "overview": "The enigmatic resurrection, rampage, and retribution of an undead monster in a remote wilderness unleashes an iconic new killer after a locket is removed from a collapsed fire tower that entombed its rotting corpse.",
  "poster_path": "https://image.tmdb.org/t/p/w500/hPfWHgq07nXbeldwEGxWB4JqwtE.jpg",
  "imdb_id": "tt30321146",
  "id": 1214509,
  "type": "movie"
}