{
  "title": "What Dreams May Come",
  "release_date": "1998-10-02",
  "vote_average": 7.2,
  "genres": "Drama, Fantasy, Romance",
  "overview": "Chris Neilson dies to find himself in a heaven more amazing than he could have ever dreamed of. There is one thing missing: his wife. After he dies, his wife, Annie killed herself and went to hell. Chris decides to risk eternity in hades for the small chance that he will be able to bring her back to heaven.",
  "poster_path": "https://image.tmdb.org/t/p/w500/2gUfJKfJ6LwdqQebiAWuNzIWyp9.jpg",
  "imdb_id": "tt0120889",
  "id": 12159,
  "type": "movie"
}