{
  "title": "Longlegs",
  "release_date": "2024-07-10",
  "vote_average": 6.722,
  "genres": "Horror, Mystery, Thriller, Crime",
  "overview": "FBI Agent Lee Harker is assigned to an unsolved serial killer case that takes an unexpected turn, revealing evidence of the occult. Harker discovers a personal connection to the killer and must stop him before he strikes again.",
  "poster_path": "https://image.tmdb.org/t/p/w500/5aj8vVGFwGVbQQs26ywhg4Zxk2L.jpg",
  "imdb_id": "tt23468450",
  "id": 1226578,
  "type": "movie"
}