{
  "title": "Christy",
  "release_date": "2025-11-06",
  "vote_average": 7.857,
  "genres": "Drama, History",
  "overview": "Christy Martin never imagined life beyond her small-town roots in West Virginia—until she discovered a knack for punching people. Fueled by grit, raw determination, and an unshakable desire to win, she charges into the world of boxing under the guidance of her trainer and manager-turned-husband, Jim. But while Christy flaunts a fiery persona in the ring, her toughest battles unfold outside it—confronting family, identity, and a relationship that just might become life-or-death.",
  "poster_path": "https://image.tmdb.org/t/p/w500/dYQ63YbeHgaukE7I2d3cC9Lnoor.jpg",
  "imdb_id": "tt32323252",
  "id": 1287322,
  "type": "movie"
}