{
  "title": "Tell Me Lies",
  "release_date": "2022-09-07",
  "vote_average": 7.4,
  "genres": "Drama, Mystery",
  "overview": "When Lucy Albright arrives on the campus of her small college, away from her mother whom she's never forgiven for an act of betrayal in her early teen years, Lucy embraces college life and all it has to offer. But everything changes when she meets Stephen DeMarco, who has a mysterious past of his own. Their addicting entanglement will have consequences they never could have imagined.",
  "poster_path": "https://image.tmdb.org/t/p/w500/tcblBr3dm0lixbEWtbITUfe9vNp.jpg",
  "imdb_id": "NO ID",
  "id": 130464,
  "type": "tv"
}