{
  "title": "Our Secret",
  "release_date": "2021-08-10",
  "vote_average": 7.1,
  "genres": "Drama",
  "overview": "From high school to university, Ding Xian and Zhou Si Yue's youthful love lasts for a lifetime. The superior and unruly campus god Zhou Si Yue is a genius. He is seatmates with the headstrong and adorable \"Cinderella girl\" Ding Xian. Although they couldn't stand one another at first, they come to appreciate each other's strengths in their day-to-day interactions, thus becoming lifelong companions in their journey through youth.",
  "poster_path": "https://image.tmdb.org/t/p/w500/duMf1Pz1f2rWQUBrzifU9knFbJu.jpg",
  "imdb_id": "NO ID",
  "id": 130822,
  "type": "tv"
}