{
  "title": "How the Grinch Stole Christmas!",
  "release_date": "1966-12-18",
  "vote_average": 7.493,
  "genres": "Animation, Family, Comedy",
  "overview": "Bitter and hateful, the Grinch is irritated at the thought of a nearby village having a happy time celebrating Christmas. Disguised as Santa Claus, with his dog made to look like a reindeer, he decides to raid the village to steal all the Christmas things.",
  "poster_path": "https://image.tmdb.org/t/p/w500/7ir0iRuPK9OEuH569cp0nF5CJce.jpg",
  "imdb_id": "tt0060345",
  "id": 13377,
  "type": "movie"
}