{
  "title": "Reset",
  "release_date": "2022-01-11",
  "vote_average": 8.123,
  "genres": "Drama, Mystery",
  "overview": "The lives of a college student and a video game designer are kept being reset after an explosion on a bus. During each reset, they have to work together to find out what the reason for the explosion is. Will these two be able to save themselves and their fellow passengers? Will they be able to close the time-loop?",
  "poster_path": "https://image.tmdb.org/t/p/w500/t95T31wxF0ElSwUE4U8AnOSAmF3.jpg",
  "imdb_id": "NO ID",
  "id": 155441,
  "type": "tv"
}