{
  "title": "Death Race: Inferno",
  "release_date": "2013-01-04",
  "vote_average": 5.844,
  "genres": "Action, Science Fiction, Thriller",
  "overview": "Carl Lucas / Frankenstein has won four of his races and needs to win one more to win his freedom. Before his final race, Lucas and his team, car and all, are transferred to another prison where they will compete in a Death Race in the desert. Also, at the same time, Ceaser runs into a marketer who wants to franchise the Death Race program.",
  "poster_path": "https://image.tmdb.org/t/p/w500/aRV4oC61nmBqypSaXtMXOk99dOM.jpg",
  "imdb_id": "tt1988591",
  "id": 156717,
  "type": "movie"
}