{
  "title": "31st",
  "release_date": "2024-12-20",
  "vote_average": 0,
  "genres": "Crime, Drama",
  "overview": "Kinjal becomes a victim of a brutal rape by her boyfriend on the 31st December.  After facing injustice by the police force, she takes her own life. Her sister takes upon the legal battle to get her sister Justice. Will Kinjal get justice?",
  "poster_path": "https://image.tmdb.org/t/p/w500/98Bu2HifjVmf5DfQzF3Wya4shpS.jpg",
  "imdb_id": "tt31474349",
  "id": 1585757,
  "type": "movie"
}