{
  "title": "V/H/S/2",
  "release_date": "2013-06-06",
  "vote_average": 6.213,
  "genres": "Horror, Thriller",
  "overview": "Inside a darkened house looms a column of TVs littered with VHS tapes, a pagan shrine to forgotten analog gods. The screens crackle and pop endlessly with monochrome vistas of static white noise permeating the brain and fogging concentration. But you must fight the urge to relax: this is no mere movie night. Those obsolete spools contain more than just magnetic tape. They are imprinted with the very soul of evil.",
  "poster_path": "https://image.tmdb.org/t/p/w500/o4hcWsHaHaNQ9BBReOxLvYJNRhA.jpg",
  "imdb_id": "tt2450186",
  "id": 159117,
  "type": "movie"
}