{
  "title": "We Are What We Are",
  "release_date": "2013-09-27",
  "vote_average": 5.763,
  "genres": "Drama, Horror, Thriller",
  "overview": "The Parkers, reclusive people who cling to ancient customs, find their secret lives threatened when a torrential downpour and the death of the family matriarch forces daughters Iris and Rose to assume special responsibilities.",
  "poster_path": "https://image.tmdb.org/t/p/w500/3Q0rtUfNHFOEnVoRv1pmKaAbZEV.jpg",
  "imdb_id": "tt2309021",
  "id": 159128,
  "type": "movie"
}