{
  "title": "Kirchiyaan",
  "release_date": "2013-01-30",
  "vote_average": 8,
  "genres": "",
  "overview": "A real time story. How a bizarre incident in a Chhattarpur farm changes the lives of so many people. How the past comes back to redeem itself. How lives get shattered and cleaned up in just 15 minutes. How life offers a sudden opportunity to make it large… in just one moment.",
  "poster_path": "https://image.tmdb.org/t/p/w500null",
  "imdb_id": "tt2725022",
  "id": 170458,
  "type": "movie"
}