{
  "title": "Aguirre, the Wrath of God",
  "release_date": "1972-12-29",
  "vote_average": 7.465,
  "genres": "History, Adventure, Drama",
  "overview": "A few decades after the destruction of the Inca Empire, a Spanish expedition led by the infamous Aguirre leaves the mountains of Peru and goes down the Amazon River in search of the lost city of El Dorado. When great difficulties arise, Aguirre’s men start to wonder whether their quest will lead them to prosperity or certain death.",
  "poster_path": "https://image.tmdb.org/t/p/w500/A3fVlnAasRXq9ZFaaZ744EvreQO.jpg",
  "imdb_id": "tt0068182",
  "id": 2000,
  "type": "movie"
}