{
  "title": "Thalaivaa",
  "release_date": "2013-08-20",
  "vote_average": 5.3,
  "genres": "Action, Drama, Thriller",
  "overview": "A mafia don sends his son out of the country because he doesn't want even a shadow of his life falling on him. Destiny wills otherwise. The son makes an innocuous trip to Mumbai to visit his dad. And ends up filling his father's large shoes.",
  "poster_path": "https://image.tmdb.org/t/p/w500/5h2SfwKTbbp0T21kjrOPU3QMaHn.jpg",
  "imdb_id": "tt2617676",
  "id": 202616,
  "type": "movie"
}