{
  "title": "A Chinese Odyssey Part Two: Cinderella",
  "release_date": "1995-02-04",
  "vote_average": 7.702,
  "genres": "Action, Adventure, Fantasy, Comedy, Romance",
  "overview": "This sequel to \"Pandora's Box\" continues director Jeffrey Lau's adaptation of the Buddhism saga \"Journey to the West\". Stranded five centuries in the past, Joker Monkey King must battle a variety of monsters, seductive women and super-powered villains to save the dying Pak Jing-Jing.",
  "poster_path": "https://image.tmdb.org/t/p/w500/jhtjo8SB9Ki0YgvHT2Ukqwqnjce.jpg",
  "imdb_id": "tt0114996",
  "id": 21835,
  "type": "movie"
}