{
  "title": "Vyooham",
  "release_date": "2023-12-14",
  "vote_average": 7.5,
  "genres": "Drama, Crime",
  "overview": "A newly appointed police officer is assigned to a hit and run case, where a pregnant couple lost their child. What seems like a simple open and shut case, turns out to be a complicated web involving several seemingly unconnected people. To solve the case, the officer has to hunt down a serial killer, a trained Naxal, a suspended cop, and a terrorist organization, while facing his own painful past.",
  "poster_path": "https://image.tmdb.org/t/p/w500/nwDqwRlBVe8hQAoLgPKQ4SfuUrC.jpg",
  "imdb_id": "NO ID",
  "id": 241347,
  "type": "tv"
}