{
  "title": "Eyes of Wakanda",
  "release_date": "2025-08-01",
  "vote_average": 4.906,
  "genres": "Animation, Action & Adventure, Sci-Fi & Fantasy",
  "overview": "Follow the adventures of brave Wakandan warriors throughout history in this globe-trotting adventure, where they must carry out dangerous missions to retrieve Vibranium artifacts from the enemies of Wakanda. They are the Hatut Zaraze and this is their story.",
  "poster_path": "https://image.tmdb.org/t/p/w500/yuOfb1MgnaGPa4guzV0n1IFYVGN.jpg",
  "imdb_id": "NO ID",
  "id": 241388,
  "type": "tv"
}