{
  "title": "Streets of Gold: Mumbai",
  "release_date": "2024-01-08",
  "vote_average": 8,
  "genres": "Documentary, Reality",
  "overview": "A look into the lives of the movers and shakers who have shaped the story of modern Mumbai, with privileged access to people who have been instrumental in turning the city into a global powerhouse. Through personal stories set against the unfolding story of the past 30 years, this episode looks at the challenges and triumphs of a city and a country in the midst of extraordinary transformation.",
  "poster_path": "https://image.tmdb.org/t/p/w500/hE1KIyt9D1RbOSxFTEeVp2soEiA.jpg",
  "imdb_id": "NO ID",
  "id": 242748,
  "type": "tv"
}