{
  "title": "Khauf",
  "release_date": "2025-04-18",
  "vote_average": "NO RATING",
  "genres": "Drama, Mystery",
  "overview": "Madhu moves into a hostel in Delhi to start afresh, but her room hides a sinister presence that begins to get stronger each day, alarming the other women on her floor. They know what the room hides and desperately want her gone before it is too late for them all.",
  "poster_path": "https://image.tmdb.org/t/p/w500/FsyjOPXYPlDqvGpw9onJsxzBQM.jpg",
  "imdb_id": "NO ID",
  "id": 249749,
  "type": "tv"
}