{
  "title": "My Dearest Nemesis",
  "release_date": "2025-02-17",
  "vote_average": 7.5,
  "genres": "Comedy, Drama",
  "overview": "As a high school senior, Su-Jeong began playing an online game where she met another player nicknamed “Black Dragon.” They unexpectedly got close, developing crushes and planning a meeting in real life… that concluded in humiliation and disaster when “Black Dragon” turned out to be an awkward middle schooler instead of the young man he portrayed himself to be!\n\nSixteen years later, Su-Jeong is a skilled planner at Yongseong Department Store, but her job is about to get a shakeup with the arrival of Ban Ju-Yeon, the ambitious new head of strategic planning and heir to the company. There’s just one problem: Ban Ju-Yeon is actually “Black Dragon,” and Su-Jeong still holds a grudge. Will their past come back to haunt them, or can they find a way to resolve their misunderstandings – and even find love as adults?\n\nBased on the webtoon \"That Man Is Black Salt Dragon\" (그 남자는 흑염룡).",
  "poster_path": "https://image.tmdb.org/t/p/w500/obxTkvATqU8a65XDOFOQeZKd3PF.jpg",
  "imdb_id": "NO ID",
  "id": 259015,
  "type": "tv"
}