{
  "title": "The Cloud Door",
  "release_date": "1994-09-28",
  "vote_average": 5.1,
  "genres": "Drama, Romance",
  "overview": "A very clever parrot lives in a Hindu palace, surrounded by many beautiful girls, but the parrot escapes, and is trapped far from the palace. One day, when its new owner is sleeping, the bird convinces a young boy to open the cage door. In return, it shows the boy a secret passage to get into the palace.",
  "poster_path": "https://image.tmdb.org/t/p/w500/iOlvgAffA3q3EcBP4ymvmgChaqs.jpg",
  "imdb_id": "tt0112694",
  "id": 261421,
  "type": "movie"
}