{
  "title": "Googly",
  "release_date": "2013-07-19",
  "vote_average": 7.1,
  "genres": "Comedy, Romance",
  "overview": "Googly is a 2013 Kannada romantic comedy film directed by Pawan Wadeyar and produced by Jayanna Combines. Yash and Kriti Kharbanda are the lead actors while Ananth Nag and Sadhu Kokila play the primary supporting roles. The film released on 19 July 2013 and opened to a fantastic response at the box office. The film was declared a \"Blockbuster\".",
  "poster_path": "https://image.tmdb.org/t/p/w500/msmmN0U0Pp9eZsxwiMlj9MIlAAm.jpg",
  "imdb_id": "tt3075360",
  "id": 267618,
  "type": "movie"
}