{
  "title": "Pappan Priyappetta Pappan",
  "release_date": "1986-07-04",
  "vote_average": 6.4,
  "genres": "Comedy",
  "overview": "A singer Pappan (Rahman) is killed in a bike accident, but Yamaraj the Lord of Death (Thilakan) realizes that Pappan has a few more days to live. Yamarajan allows Pappan to enter into bodies of other dead people including that of Inspector Devdas (Mohanlal) in a bid to tell his girlfriend Sarina (Lizy) that Pappan is dead, and to look forward to someone else in life.",
  "poster_path": "https://image.tmdb.org/t/p/w500/1SESGQJSuUpLbKxSHiyHNUBDjaw.jpg",
  "imdb_id": "tt0282827",
  "id": 280340,
  "type": "movie"
}