{
  "title": "Frankenstein Meets the Wolf Man",
  "release_date": "1943-03-05",
  "vote_average": 6.205,
  "genres": "Horror, Science Fiction",
  "overview": "Grave robbers open the grave of the wolf man and awaken him. He doesn't like the idea of being immortal and killing people when the moon is full so tries to find Dr. Frankenstein, in the hopes that the doctor can cure him. Dr. Frankenstein has died; however, his monster is found.",
  "poster_path": "https://image.tmdb.org/t/p/w500/eitxewmvmZXY7qoKpiVhdaFmwMz.jpg",
  "imdb_id": "tt0035899",
  "id": 3076,
  "type": "movie"
}