{
  "title": "Uncharted",
  "release_date": "2022-02-10",
  "vote_average": 6.944,
  "genres": "Action, Adventure",
  "overview": "A young street-smart, Nathan Drake and his wisecracking partner Victor “Sully” Sullivan embark on a dangerous pursuit of “the greatest treasure never found” while also tracking clues that may lead to Nathan’s long-lost brother.",
  "poster_path": "https://image.tmdb.org/t/p/w500/rJHC1RUORuUhtfNb4Npclx0xnOf.jpg",
  "imdb_id": "tt1464335",
  "id": 335787,
  "type": "movie"
}