{
  "title": "India Pakistan",
  "release_date": "2015-05-08",
  "vote_average": 5.3,
  "genres": "Comedy, Romance",
  "overview": "It is only after moving in to their shared office space do Karthick and Mellina realize that they are in the same profession — law. So, they decide that whoever gets a case first will stay in the place and fight tooth-and-nail to get a case. Meanwhile, a cop, who is searching for a DVD containing video of his illegal encounter, is after Mellina thinking that she is in possession of it.",
  "poster_path": "https://image.tmdb.org/t/p/w500/yqLODRtuvqm9jIGAeH4a37OdBwn.jpg",
  "imdb_id": "tt4672350",
  "id": 336259,
  "type": "movie"
}