{
  "title": "Chinna Thambi Periya Thambi",
  "release_date": "1987-02-27",
  "vote_average": 6.2,
  "genres": "",
  "overview": "Prabhu and Sathyaraj are brothers who fall in love with their uncle's daughter Nadia. Nadiya is initially arranged to marry a wealthy man but due to dire circumstances the wedding is called off.She then goes back to the village and starts to live with her uncles and grandmother.Eventually she falls in love with Prabhu,meanwhile, Sathyaraj happens to rescue a widow Sudha Chandran from dire straits, and falls for her.The story ends with both the brothers happily married.",
  "poster_path": "https://image.tmdb.org/t/p/w500/88tZ0lrbPnbCnI74SOgpX1wZHz.jpg",
  "imdb_id": "tt0308113",
  "id": 361056,
  "type": "movie"
}