{
  "title": "Here Comes Mr. Jordan",
  "release_date": "1941-08-07",
  "vote_average": 6.9,
  "genres": "Comedy, Fantasy, Romance",
  "overview": "Boxer Joe Pendleton, flying to his next fight, crashes...because a Heavenly Messenger, new on the job, snatched Joe's spirit prematurely from his body. Before the matter can be rectified, Joe's body is cremated; so the celestial Mr. Jordan grants him the use of the body of wealthy Bruce Farnsworth, who's just been murdered by his wife. Joe tries to remake Farnsworth's unworthy life in his own clean-cut image, but then falls in love; and what about that murderous wife?",
  "poster_path": "https://image.tmdb.org/t/p/w500/k6gmIV3hTSCG2JBh2zPMLogZ5y3.jpg",
  "imdb_id": "tt0033712",
  "id": 38914,
  "type": "movie"
}