{
  "title": "The Switch",
  "release_date": "2010-05-11",
  "vote_average": 6.229,
  "genres": "Comedy, Romance, Drama",
  "overview": "Kassie is a smart, fun-loving single woman who, despite her neurotic best friend Wally’s objections, decides it’s time to have a baby – even if it means doing it herself… with a little help from a charming sperm donor. But, unbeknownst to her, Kassie’s plans go awry because of a last-minute switch that isn’t discovered until seven years later… when Wally gets acquainted with Kassie’s cute, though slightly neurotic, son.",
  "poster_path": "https://image.tmdb.org/t/p/w500/oJdMT6RGtbvQ26Tk7EHGfG8xZ6.jpg",
  "imdb_id": "tt0889573",
  "id": 41210,
  "type": "movie"
}