{
  "title": "Final Score",
  "release_date": "2018-09-07",
  "vote_average": 6.1,
  "genres": "Action, Thriller, Adventure, Drama",
  "overview": "When a stadium is seized by a group of heavily armed criminals during a major sporting event, an ex-soldier must use all his military skills to save both the daughter of a fallen comrade and the huge crowd unaware of the danger.",
  "poster_path": "https://image.tmdb.org/t/p/w500/5m3FEfxGQ7MdNNfUwNtA6paXRDs.jpg",
  "imdb_id": "tt5254610",
  "id": 421658,
  "type": "movie"
}