{
  "title": "Romance on the High Seas",
  "release_date": "1948-06-25",
  "vote_average": 6.7,
  "genres": "Comedy, Romance",
  "overview": "Georgia Garrett is sent by jealous wife Elvira Kent on an ocean cruise to masquerade as herself while she secretly stays home to catch her husband cheating. Meanwhile equally suspicious husband Michael Kent has sent a private eye on the same cruise to catch his wife cheating. Love and confusion ensues along with plenty of musical numbers.",
  "poster_path": "https://image.tmdb.org/t/p/w500/60YafJKLwCINwD7Q10yWXDpAGt3.jpg",
  "imdb_id": "tt0040745",
  "id": 43449,
  "type": "movie"
}