{
  "title": "The Hate U Give",
  "release_date": "2018-10-19",
  "vote_average": 8.1,
  "genres": "Crime, Drama",
  "overview": "Raised in a poverty-stricken slum, a 16-year-old girl named Starr now attends a suburban prep school. After she witnesses a police officer shoot her unarmed best friend, she's torn between her two very different worlds as she tries to speak her truth.",
  "poster_path": "https://image.tmdb.org/t/p/w500/2icwBom0t5nmOuZI9FVXF3gkMK0.jpg",
  "imdb_id": "tt5580266",
  "id": 470044,
  "type": "movie"
}