{
  "title": "Cannibal",
  "release_date": "2006-12-05",
  "vote_average": 5.3,
  "genres": "Drama, Horror, Thriller, Crime",
  "overview": "Cannibal is based on the true-crime story of Armin Meiwes, the \"Rotenburg Cannibal\" who posted an online ad searching for someone to volunteer to be mutilated and eaten. Unlikely as it may seem, someone actually replied. The film shows a fictional portrayal of the meeting between the cannibal and his victim/participant, their homosexual relationship, and the eventual mutilation and murder of said victim.",
  "poster_path": "https://image.tmdb.org/t/p/w500/61JCuNGRTrPWFIPuqSNaQ5Lz5Ve.jpg",
  "imdb_id": "tt0910548",
  "id": 48753,
  "type": "movie"
}