{
  "title": "Love Shack",
  "release_date": "2010-11-23",
  "vote_average": 2,
  "genres": "Comedy",
  "overview": "A dysfunctional family of adult film stars reunites for a memorial porn shoot following the death of legendary producer Mo Saltzman. Along the way, the film's hapless director must contend with dueling divas, bickering couples, emotionally-scarred tag-team brothers, and a dominatrix with low self-esteem. Given its all-star cast and lofty pedigree, the film should be the greatest porno of all time",
  "poster_path": "https://image.tmdb.org/t/p/w500/sFZ3y7AYZzAUEH2bbaRpp9uJPU2.jpg",
  "imdb_id": "tt1445675",
  "id": 50653,
  "type": "movie"
}