{
  "title": "Lessons of Darkness",
  "release_date": "1992-02-21",
  "vote_average": 7.845,
  "genres": "War, Documentary",
  "overview": "Shortly after the Gulf War, oil fires were raging all through Kuwait. In the week before this sea of fire would be extinguished, Werner Herzog filmed this apocalyptic landscape with its murky skies, scorched earth and capricious flames.",
  "poster_path": "https://image.tmdb.org/t/p/w500/rSQaIbOQj6SUSOxr3BEiAmCoj1P.jpg",
  "imdb_id": "tt0104706",
  "id": 53200,
  "type": "movie"
}