{
  "title": "Flamin' Hot",
  "release_date": "2023-03-11",
  "vote_average": 7.944,
  "genres": "Drama, History",
  "overview": "The inspiring true story of Richard Montañez, the Frito Lay janitor who channeled his Mexican American heritage and upbringing to turn the iconic Flamin' Hot Cheetos into a snack that disrupted the food industry and became a global pop culture phenomenon.",
  "poster_path": "https://image.tmdb.org/t/p/w500/a7KyFMPXj0iY4EoLq1PIGU1WJPw.jpg",
  "imdb_id": "tt8105234",
  "id": 626332,
  "type": "movie"
}