{
  "title": "Gamak Ghar",
  "release_date": "2019-10-18",
  "vote_average": 9,
  "genres": "Drama, Family",
  "overview": "In a north Indian village, a family reunites at their ancestral home to celebrate a new birth in the family. It’s a joyous, carefree occasion. Over the next two decades, through festivals and feasts, births and deaths, the film observes one house as it ages and falls to neglect.",
  "poster_path": "https://image.tmdb.org/t/p/w500/ir2Y4N2I8L2W95JI7byURRoJr80.jpg",
  "imdb_id": "tt10518934",
  "id": 629321,
  "type": "movie"
}