{
  "title": "Samurai Cop",
  "release_date": "1991-11-30",
  "vote_average": 4.6,
  "genres": "Action, Crime, Comedy, Thriller",
  "overview": "When Japanese organized crime imbeds itself within LA, the police turn to one man to take down the deadly Yakuza — Joe Marshall, aka \"The Samurai.\" With his fearless swagger and rock hard jaw, The Samurai tears a two-fisted hole through the mob and doesn't stop until the job is done.",
  "poster_path": "https://image.tmdb.org/t/p/w500/jOlz0kpxlLY5xixyDYpcYUi2SJy.jpg",
  "imdb_id": "tt0130236",
  "id": 65374,
  "type": "movie"
}