{
  "title": "Ponniyin Selvan: Part I",
  "release_date": "2022-09-30",
  "vote_average": 7.056,
  "genres": "Action, Adventure",
  "overview": "The Chola kingdom is under threat from forces both internal and external, and with crown prince Aaditha Karikalan, his younger brother Arunmozhi Varman and the emperor, Sundara Cholar separated by situations, it is up to a messenger to ensure the safety of the kingdom. Can he succeed in his mission, especially with Karikalan's former girlfriend, Nandhini, plotting to bring down the entire Chola empire?",
  "poster_path": "https://image.tmdb.org/t/p/w500/zSNyZUeqDdii0doQ9970E90kCkb.jpg",
  "imdb_id": "tt10701074",
  "id": 660046,
  "type": "movie"
}