{
  "title": "Censor",
  "release_date": "2021-06-11",
  "vote_average": 5.822,
  "genres": "Horror, Mystery",
  "overview": "A screener at the British Board of Film Classification (BBFC), who has earned an unsavory reputation for being the strictest censor of violent films, begins to spiral out of control after viewing a low-budget horror with similarities to the disappearance of her sister.",
  "poster_path": "https://image.tmdb.org/t/p/w500/1FOEEtGFPp5cgpLfPQVMB0UNVpI.jpg",
  "imdb_id": "tt10329614",
  "id": 663866,
  "type": "movie"
}