{
  "title": "Lunchbox",
  "release_date": "2019-01-09",
  "vote_average": 7,
  "genres": "Drama",
  "overview": "Antonin is a young miner. He is daydreamer and he would like to find a motivation to keep working in the mine. One day he notices a sun shape on the rice served in the lunchbox. It becomes a daily routine to see a new shape every lunch time.",
  "poster_path": "https://image.tmdb.org/t/p/w500/jTsZdz1dclRKRV72aob4PdHUZoG.jpg",
  "imdb_id": "tt8755302",
  "id": 701346,
  "type": "movie"
}