{
  "title": "Aaron",
  "release_date": "2018-12-07",
  "vote_average": 9.5,
  "genres": "",
  "overview": "Babu, a fifteen-year-old boy from a small village in Konkan (Maharashtra), has not met his mother for many years due to her work in Paris. The boy and his uncle, who is entrusted with the responsibility of taking him to his mother, start their journey to Paris, which turns out to be an unforgettable sojourn for them. Babu's quest to meet his mother with the help of his uncle reveals many dimensions of human nature, feelings, and emotions.",
  "poster_path": "https://image.tmdb.org/t/p/w500/g6EN9ftN2XJF78xwf6Bon7wH07P.jpg",
  "imdb_id": "tt6616244",
  "id": 718005,
  "type": "movie"
}