{
  "title": "War of the Worlds",
  "release_date": "2005-06-28",
  "vote_average": 6.511,
  "genres": "Adventure, Thriller, Science Fiction",
  "overview": "Ray Ferrier is a divorced dockworker and less-than-perfect father. Soon after his ex-wife and her new husband drop off his teenage son and young daughter for a rare weekend visit, a strange and powerful lightning storm touches down.",
  "poster_path": "https://image.tmdb.org/t/p/w500/6Biy7R9LfumYshur3YKhpj56MpB.jpg",
  "imdb_id": "tt0407304",
  "id": 74,
  "type": "movie"
}