{
  "title": "Smokin' Aces",
  "release_date": "2006-12-09",
  "vote_average": 6.486,
  "genres": "Action, Comedy, Crime, Thriller",
  "overview": "When a Las Vegas performer-turned-snitch named Buddy Israel decides to turn state's evidence and testify against the mob, it seems that a whole lot of people would like to make sure he's no longer breathing.",
  "poster_path": "https://image.tmdb.org/t/p/w500/nrdnN8WqvyOt8Bnl3hgWcZD6ZyM.jpg",
  "imdb_id": "tt0475394",
  "id": 7516,
  "type": "movie"
}