{
  "title": "Freedom @ Midnight",
  "release_date": "2021-01-09",
  "vote_average": 6.2,
  "genres": "Drama",
  "overview": "On a rainy evening, Chandra decides to reveal an intimate matter to her husband, Das. It would change their worlds forever shattering whatever they had known about each other. Would they be having the strength to continue their lives as usual after realizing that truth?",
  "poster_path": "https://image.tmdb.org/t/p/w500/mJvIDpJmslIWpDjJgERQCrNIooX.jpg",
  "imdb_id": "tt13839622",
  "id": 786128,
  "type": "movie"
}