{
  "title": "Wild Dog",
  "release_date": "2021-04-02",
  "vote_average": 5.6,
  "genres": "Action, Thriller",
  "overview": "Wild Dog aka Vijay Varma is an NIA agent who’s brought back to field from a desk job to handle a terrorism case. Despite having a personal motive, he moves heaven and earth to ensure justice is served for the sake of the country.",
  "poster_path": "https://image.tmdb.org/t/p/w500/8377XckHbfJDMrkSpEa9ZQJlVE0.jpg",
  "imdb_id": "tt11503178",
  "id": 802068,
  "type": "movie"
}