{
  "title": "Siyavar Ram",
  "release_date": "2020-11-14",
  "vote_average": 0,
  "genres": "Animation",
  "overview": "Born during an age when the demon Ravana terrorized the world, Rama is the virtuous, wise, and powerful prince of Ayohya. As a young man, he is able to accomplish what no other man has ever done: he lifts and strings the bow of Siva, and by so doing her earns the right to marry the beautiful Sita.",
  "poster_path": "https://image.tmdb.org/t/p/w500/lWFW7H2w5oVmujMRyWPucOBumgs.jpg",
  "imdb_id": "tt13534804",
  "id": 821902,
  "type": "movie"
}