{
  "title": "M",
  "release_date": "2023-10-05",
  "vote_average": 7.5,
  "genres": "Science Fiction, Drama, Adventure, Horror",
  "overview": "Deep in a secluded forest, Marko lives in isolation under the watchful eye of his overprotective father, who is determined to keep his young son safe from the Evil Ones. Deeply lonely, and increasingly curious about the outside world, Marko yearns to uncover the secrets of life beyond the forest and begins venturing further from home. But after a cruel turn of events grants his wish sooner than he ever imagined, Marko is forced to flee and embark on a grim journey filled with unknown dangers and a glimpse into a world forever changed.",
  "poster_path": "https://image.tmdb.org/t/p/w500/rESIobLEipch59C8Qr0tRXufHYX.jpg",
  "imdb_id": "tt11076026",
  "id": 829361,
  "type": "movie"
}