{
  "title": "All the Crows in the World",
  "release_date": "2021-06-13",
  "vote_average": 5.625,
  "genres": "Drama, Comedy",
  "overview": "18-year-old Shengnan is invited to a mysterious party by her cousin. Upon arrival, Shengnan finds herself surrounded by greasy middle-aged men, with the exception of Jianguo, who is different. Shengnan and Jianguo decide to bail on the party, embarking on a night of adventures in the adult world.",
  "poster_path": "https://image.tmdb.org/t/p/w500/reNIRDL1gkYN1cuBAY1AiESrurF.jpg",
  "imdb_id": "tt14994868",
  "id": 843024,
  "type": "movie"
}