{
  "title": "Lines",
  "release_date": "2021-07-29",
  "vote_average": 7,
  "genres": "Drama",
  "overview": "Nazia is a simple girl from a village close to the borderlines who gets married to Nabeel, the grandson of Nooran from across the border. Nazia's happiness is quashed when a war starts between the two nations. Will Nazia be reunited with her love?",
  "poster_path": "https://image.tmdb.org/t/p/w500/wmUxXlzDkdpLUxxEgZbyUYDEhhN.jpg",
  "imdb_id": "tt9603216",
  "id": 855414,
  "type": "movie"
}