{
  "title": "Bhola Shankar",
  "release_date": "2023-08-10",
  "vote_average": 5.7,
  "genres": "Action, Crime, Drama, Thriller",
  "overview": "A reformed gangster now taxi driver unwittingly draws the vengeance of a crime syndicate after aiding the police in busting a smuggling operation. Fueled by a burning desire for justice and to protect his adopted sister, he embarks on a relentless quest to hunt down the mobsters responsible.",
  "poster_path": "https://image.tmdb.org/t/p/w500/hgip2gbwu19ITJw1KvzLjKHIInt.jpg",
  "imdb_id": "tt13131610",
  "id": 864221,
  "type": "movie"
}