{
  "title": "Mili",
  "release_date": "2022-11-04",
  "vote_average": 6.3,
  "genres": "Thriller",
  "overview": "Mili Naudiyal, a nursing graduate is planning to move to Canada. She takes up a job at a food outlet for the time being but her sudden disappearance without a clue leaves her loved ones in a desperate search for her in this survival drama.",
  "poster_path": "https://image.tmdb.org/t/p/w500/eJ36QCd5SPRpivJkVgZMqKyfgCz.jpg",
  "imdb_id": "tt15257644",
  "id": 908397,
  "type": "movie"
}