{
  "title": "S.W.A.T.",
  "release_date": "2003-08-08",
  "vote_average": 6.159,
  "genres": "Action, Thriller, Crime",
  "overview": "Hondo Harrelson recruits Jim Street to join an elite unit of the Los Angeles Police Department. Together they seek out more members, including tough Deke Kay and single mom Chris Sanchez. The team's first big assignment is to escort crime boss Alex Montel to prison. It seems routine, but when Montel offers a huge reward to anyone who can break him free, criminals of various stripes step up for the prize.",
  "poster_path": "https://image.tmdb.org/t/p/w500/bon63yPVIgUFLP2653Dg9GCOJLJ.jpg",
  "imdb_id": "tt0257076",
  "id": 9257,
  "type": "movie"
}