{
  "title": "Starsky & Hutch",
  "release_date": "2004-03-05",
  "vote_average": 5.8,
  "genres": "Comedy, Crime",
  "overview": "Join uptight David Starsky and laid-back Ken \"Hutch\" Hutchinson as they're paired for the first time as undercover cops. The new partners must overcome their differences to solve an important case with help from street informant Huggy Bear and persuasive criminal Reese Feldman.",
  "poster_path": "https://image.tmdb.org/t/p/w500/fmBYVkBjhVspPv3GGus84qhBo1a.jpg",
  "imdb_id": "tt0335438",
  "id": 9384,
  "type": "movie"
}