{
  "title": "Darja",
  "release_date": "2022-07-22",
  "vote_average": 7,
  "genres": "Action",
  "overview": "Kanaka Mahalaksmi is a local don, who does liquor business in Bandhar city and known for her ruthlessness. She sets her sights to rule the Bandhar port. As everyone including the police are terrified by her, ACP Shiva Shankar is transferred to the same city to get the crimes under control. The face off and the clash between these two powerful characters makes the rest of the story.",
  "poster_path": "https://image.tmdb.org/t/p/w500/gnqybDXJFHn3HjNrPjLlbJnOiYW.jpg",
  "imdb_id": "tt15840614",
  "id": 954512,
  "type": "movie"
}