{
  "title": "American Carnage",
  "release_date": "2022-07-15",
  "vote_average": 5.914,
  "genres": "Mystery, Thriller, Comedy, Horror",
  "overview": "After a governor issues an executive order to arrest the children of undocumented immigrants, the detained youth are offered an opportunity to have their charges dropped by volunteering to provide care to the elderly. Once inside the elder care facility, however, they discover more twisted secrets than they could have possibly imagined.",
  "poster_path": "https://image.tmdb.org/t/p/w500/zQmwQqtT2KEfg5IO5u8lexZoCAR.jpg",
  "imdb_id": "tt20672490",
  "id": 982752,
  "type": "movie"
}