{
  "title": "The Man Who Would Be King",
  "release_date": "1975-12-03",
  "vote_average": 7.484,
  "genres": "Adventure, Drama",
  "overview": "A robust adventure about two British adventurers who take over primitive Kafiristan as \"godlike\" rulers, meeting a tragic end through their desire for a native girl. Based on a short story by Rudyard Kipling.",
  "poster_path": "https://image.tmdb.org/t/p/w500/gc5fS9UfNrGm5cBlbAI560YbDSF.jpg",
  "imdb_id": "tt0073341",
  "id": 983,
  "type": "movie"
}